docwalker/__init__.py
docwalker/__main__.py
docwalker/app.py
docwalker/cli.py
docwalker/parser.py
docwalker/styles/main.css
docwalker-1.0.2.dist-info/entry_points.txt
docwalker-1.0.2.dist-info/LICENSE
docwalker-1.0.2.dist-info/METADATA
docwalker-1.0.2.dist-info/WHEEL
docwalker-1.0.2.dist-info/RECORD
