Metadata-Version: 2.1
Name: docwalker
Version: 1.0.2
Summary: Quickly view documentation in source code in a language-agnostic way.
License: MIT
Keywords: tui,documentation,viewer
Author: Conner Marzen
Author-email: connermarzen@gmail.com
Requires-Python: >=3.7,<4.0
Classifier: Development Status :: 4 - Beta
Classifier: Intended Audience :: Developers
Classifier: License :: OSI Approved :: MIT License
Classifier: Programming Language :: Python :: 3
Classifier: Programming Language :: Python :: 3.7
Classifier: Programming Language :: Python :: 3.8
Classifier: Programming Language :: Python :: 3.9
Classifier: Programming Language :: Python :: 3.10
Classifier: Programming Language :: Python :: 3.11
Classifier: Programming Language :: Python :: 3 :: Only
Requires-Dist: textual (>=0.29.0,<0.30.0)
